logypy/__init__.py
logypy/logypy.py
logypy-0.0.1.dist-info/METADATA
logypy-0.0.1.dist-info/WHEEL
logypy-0.0.1.dist-info/top_level.txt
logypy-0.0.1.dist-info/RECORD
